LICENSE.txt
MANIFEST.in
README.rst
setup.cfg
setup.py
examples/pytask_ex1.py
examples/pytask_ex2.py
pytaskpool/__init__.py
pytaskpool/pytaskpool.py
pytaskpool.egg-info/PKG-INFO
pytaskpool.egg-info/SOURCES.txt
pytaskpool.egg-info/dependency_links.txt
pytaskpool.egg-info/top_level.txt